Metadata-Version: 2.4
Name: memoryos-pro
Version: 0.1.0
Summary: A new generation of memory systems for large language models.
Author-email: Your Name <your@email.com>
License: MIT License
Project-URL: Homepage, https://github.com/pypa/sampleproject
Project-URL: Bug Tracker, https://github.com/pypa/sampleproject/issues
Classifier: Programming Language :: Python :: 3
Classifier: License :: OSI Approved :: MIT License
Classifier: Operating System :: OS Independent
Requires-Python: >=3.8
License-File: LICENSE
Requires-Dist: numpy==1.24.*
Requires-Dist: sentence-transformers<3.0.0,>=2.2.0
Requires-Dist: faiss-gpu<2.0.0,>=1.7.0
Requires-Dist: openai
Requires-Dist: flask<3.0.0,>=2.0.0
Requires-Dist: python-dotenv<2.0.0,>=0.19.0
Requires-Dist: typing-extensions<5.0.0,>=4.0.0
Requires-Dist: regex>=2022.1.18
Dynamic: license-file
